odoo10_addon_cms_form_example-10.0.1.0.0.99.dev4-nspkg.pth
odoo/addons/cms_form_example/README.rst
odoo/addons/cms_form_example/__init__.py
odoo/addons/cms_form_example/__manifest__.py
odoo/addons/cms_form_example/controllers/__init__.py
odoo/addons/cms_form_example/controllers/main.py
odoo/addons/cms_form_example/i18n/cms_form_example.pot
odoo/addons/cms_form_example/models/__init__.py
odoo/addons/cms_form_example/models/partner.py
odoo/addons/cms_form_example/static/description/icon.png
odoo/addons/cms_form_example/static/src/js/cms_form_example.tour.js
odoo/addons/cms_form_example/templates/assets.xml
odoo10_addon_cms_form_example-10.0.1.0.0.99.dev4.dist-info/METADATA
odoo10_addon_cms_form_example-10.0.1.0.0.99.dev4.dist-info/WHEEL
odoo10_addon_cms_form_example-10.0.1.0.0.99.dev4.dist-info/namespace_packages.txt
odoo10_addon_cms_form_example-10.0.1.0.0.99.dev4.dist-info/top_level.txt
odoo10_addon_cms_form_example-10.0.1.0.0.99.dev4.dist-info/RECORD
